deleteYourPDF/__init__.py
deleteYourPDF/actions.py
delete_your_pdf-1.0.1.dist-info/LICENSE
delete_your_pdf-1.0.1.dist-info/METADATA
delete_your_pdf-1.0.1.dist-info/WHEEL
delete_your_pdf-1.0.1.dist-info/top_level.txt
delete_your_pdf-1.0.1.dist-info/RECORD
